{
    "data_structure": [
        {
            "question": "Which of the following is not a disadvantage to the usage of array?",
            "choice1": "Fixed size",
            "choice2": "You know the size of the array prior to allocation",
            "choice3": "Insertion based on position",
            "choice4": "Accessing elements at specified positions",
            "answer": "Accessing elements at specified positions"
         },
         {
            "question": "What is the time complexity to count the number of elements in the linked list?",
            "choice1": "O(1)",
            "choice2": "O(n)",
            "choice3": "O(log n)",
            "choice4": "O(log n^2)",
            "answer": "O(n)"
         },
         {
            "question": "Which of these is an application of linked lists?",
            "choice1": "To store the information and the link to the next item",
            "choice2": "To check for the end of the list",
            "choice3": "Not used in a linked list",
            "choice4": "All of above",
            "answer": "To store the information and the link to the next item"
         },
         {
            "question": "What is a node used for in a linked list?",
            "choice1": "To implement file systems",
            "choice2": "For separate chaining in hash-tables",
            "choice3": "To implement non-binary trees",
            "choice4": "All of above",
            "answer": "All of above"
         },       
         {
            "question": "A linked list is a collection of?",
            "choice1": "Classes",
            "choice2": "Addresses",
            "choice3": "Nodes",
            "choice4": "Memory Variables",
            "answer": "Nodes"
         },       
         {
            "question": "Whenever a system is modeled on the First In First Out principle, are used.",
            "choice1": "Hash Table",
            "choice2": "Tree",
            "choice3": "Queue",
            "choice4": "Network",
            "answer": "Queue"
         },       
         {
            "question": "The ability to create new data types from existing data types.",
            "choice1": "Encapsulation",
            "choice2": "Information Hiding",
            "choice3": "Inheritance",
            "choice4": "Polymorphism",
            "answer": "Inheritance"
         },                
         {
            "question": "Which of the following data structures allows direct access to all of its items?",
            "choice1": "Array",
            "choice2": "Stack",
            "choice3": "Queue",
            "choice4": "Linked List",
            "answer": "Array"
         },
         {
            "question": "What is the address of the first node in the list is stored in a separate location.",
            "choice1": "Head",
            "choice2": "Key",
            "choice3": "Tail",
            "choice4": "Top",
            "answer": "Head"
         },
         {
            "question": "In a recursive solution to a problem, we solve a problem P(n) by solving another problem P(k) where",
            "choice1": "P(k) is smaller than P(n)",
            "choice2": "P(k) is same as P(n)",
            "choice3": "P(k) is the hardest part of P(n)",
            "choice4": "P(k) is larger problem than P(n)",
            "answer": "P(k) is smaller than P(n)"
         },
         {
            "question": "What is a function that contains a function call to itself?",
            "choice1": "Self-reference Function",
            "choice2": "Reciprocal Function",
            "choice3": "Repetitive Function",
            "choice4": "Recursive Function",
            "answer": "Recursive Function"
         },
         {
            "question": "If the array, [6, 2, 7, 13, 8, 5], is added to a stack, in the order given, which number will be the first number to be removed from the stack?",
            "choice1": "8",
            "choice2": "5",
            "choice3": "6",
            "choice4": "2",
            "answer": "5"
         },
         {
            "question": "What data structure is used for Breath First traversal of a graph",
            "choice1": "Queue",
            "choice2": "Stack",
            "choice3": "List",
            "choice4": "None of the above",
            "answer": "Queue"
         },
         {
            "question": "Quick Sort algorithm is an example of?",
            "choice1": "Greedy Approach",
            "choice2": "Improved Binary Search",
            "choice3": "Dynamic Programming",
            "choice4": "Divide and Conquer",
            "answer": "Divide and Conquer"
         },
         {
            "question": "Which of the following searching techniques do not require the data to be in sorted form?",
            "choice1": "Binary Search",
            "choice2": "Interpolation Search",
            "choice3": "Linear Search",
            "choice4": "All of the above",
            "answer": "Linear Search"
         },
         {
            "question": "Visting root node after visiting left and right sub-trees is called?",
            "choice1": "In-order Traversal",
            "choice2": "Pre-order Traversal",
            "choice3": "Post-order Traversal",
            "choice4": "Tree Traversal",
            "answer": "Post-order Traversal"
         },
         {
            "question": "Which of the following algorithms is not stable?",
            "choice1": "Bubble Sort",
            "choice2": "Quick Sort",
            "choice3": "Merge Sort",
            "choice4": "Insertion Sort",
            "answer": "Quick Sort"
         },
         {
            "question": "If the array is already sorted, which of these algorithms will exhibit the best performance?",
            "choice1": "Merger Sort",
            "choice2": "Insertion Sort",
            "choice3": "Quick Sort",
            "choice4": "Heap Sort",
            "answer": "Insertion Sort"
         },
         {
            "question": "Graph Traversal is different from a Tree Traversal, becasue",
            "choice1": "Trees are not connected",
            "choice2": "Graphs may have loops",
            "choice3": "Trees have root",
            "choice4": "None is true as tree is a subset of a graph",
            "answer": "Trees have root"
         },
         {
            "question": "The time complexity of Depth First Traversal is?",
            "choice1": "O(V+E)",
            "choice2": "O(V)",
            "choice3": "O(E)",
            "choice4": "O(V*E)",
            "answer": "O(V+E)"
         },
         {
            "question": "For a Binary Search Algorithm to work, it is necessary that the array(list) must be",
            "choice1": "Sorted",
            "choice2": "Unsorted",
            "choice3": "In a heap",
            "choice4": "Pooped out of a stack",
            "answer": "Sorted"
         },
         {
            "question": "What data structure is used for Depth First Traversal of a graph?",
            "choice1": "Queue",
            "choice2": "Stack",
            "choice3": "List",
            "choice4": "None of the above",
            "answer": "Stack"
         },
         {
            "question": "What data structure can be used to check if a syntax has Balanced Parentheses?",
            "choice1": "Queue",
            "choice2": "Tree",
            "choice3": "List",
            "choice4": "Stack",
            "answer": "Stack"
         },
         {
            "question": "Minimum number of queues required for priority queue implementation?",
            "choice1": "5",
            "choice2": "4",
            "choice3": "3",
            "choice4": "2",
            "answer": "2"
         },
         {
            "question": "How many swaps are required to sort the given array using bubble sort - { 2, 5, 1, 3, 4}",
            "choice1": "4",
            "choice2": "5",
            "choice3": "6",
            "choice4": "7",
            "answer": "4"
         },
         {
            "question": "In binary heap, whenever the root is removed then the rightmost element of last level is replaced by the root. Why?",
            "choice1": "It is the easiet possible way",
            "choice2": "To make sure that it is still complete binary tree",
            "choice3": "Because left and right subtree might be missing",
            "choice4": "None of the above",
            "answer": "To make sure that it is still complete binary tree"
         },
         {
            "question": "Quick Sort running time depends on the selection of",
            "choice1": "Size of array",
            "choice2": "Pivot Element",
            "choice3": "Sequence of values",
            "choice4": "Stack",
            "answer": "Pivot Element"
         },
         {
            "question": "Which of these algorithmic approach tries to achieve localized optimum solution?",
            "choice1": "Greedy Approach",
            "choice2": "Divide and Conquer Approach",
            "choice3": "Dynamic Approach",
            "choice4": "2 Pointers Approach",
            "answer": "Greedy Approach"
         },
         {
            "question": "In Doubly Linked List",
            "choice1": "A pointer is maintained to store both next and previous nodes",
            "choice2": "Two pointers are maintained to store next and previous nodes",
            "choice3": "A pointer to self is maintained for each node",
            "choice4": "None of the above",
            "answer": "Two pointers are maintained to store next and previous nodes"
         },
         {
            "question": "Heap is an example of",
            "choice1": "Complete Binary Tree",
            "choice2": "Spanning Tree",
            "choice3": "Sparse Tree",
            "choice4": "Binary Search Tree",
            "answer": "Complete Binary Tree"
         }
     ],
     "computer_science": [  
            {
               "question": "The Harvard architecture for micro-controllers added which additional bus?",
               "choice1": "Control",
               "choice2": "Instruction",
               "choice3": "Data",
               "choice4": "Address",
               "answer": "Instruction"
            },
            {
               "question": "Which company was established on April 1st, 1976 by Steve Jobs, Steve Wozniak and Ronald Wayne?",
               "choice1": "Microsoft",
               "choice2": "Commodore",
               "choice3": "Apple",
               "choice4": "Atari",
               "answer": "Apple"
            },

            {
               "question": "What amount of bits commonly equals one byte?",
               "choice1": "64",
               "choice2": "1",
               "choice3": "2",
               "choice4": "8",
               "answer": "8"
            },
            {
               "question": "Which computer hardware device provides an interface for all other connected devices to communicate?",
               "choice1": "Central Processing Unit",
               "choice2": "Hard Disk Drive",
               "choice3": "Motherboard",
               "choice4": "Random Access Memory",
               "answer": "Motherboard"
            },
            {
               "question": "On which computer hardware device is the BIOS chip located?",
               "choice1": "Motherboard",
               "choice2": "Hard Disk Drive",
               "choice3": "Central Processing Unit",
               "choice4": "Graphics Processing Unit",
               "answer": "Motherboard"
            },
            {
               "question": "What is the most preferred image format used for logos in the Wikimedia database?",
               "choice1": ".svg",
               "choice2": ".png",
               "choice3": ".jpeg",
               "choice4": ".gif",
               "answer": ".svg"
            },
            {
               "question": "In web design, what does CSS stand for?",
               "choice1": "Counter Strike: Source",
               "choice2": "Cascading Style Sheet",
               "choice3": "Corrective Style Sheet",
               "choice4": "Computer Style Sheet",
               "answer": "Cascading Style Sheet"
            },
            {
               "question": "Which of these is the name for the failed key escrow device introduced by the National Security Agency in 1993?",
               "choice1": "Skipjack",
               "choice2": "Clipper Chip",
               "choice3": "Nautilus",
               "choice4": "Enigma Machine",
               "answer": "Clipper Chip"
            },
            {
               "question": "While Apple was formed in California, in which western state was Microsoft founded?",
               "choice1": "Arizona",
               "choice2": "New Mexico",
               "choice3": "Colorado",
               "choice4": "Washington",
               "answer": "New Mexico"
            },
            {
               "question": "Generally, which component of a computer draws the most power?",
               "choice1": "Video Card",
               "choice2": "Hard Drive",
               "choice3": "Processor",
               "choice4": "Power Supply",
               "answer": "Video Card"
            },
            {
               "question": "What port does HTTP run on?",
               "choice1": "53",
               "choice2": "80",
               "choice3": "23",
               "choice4": "443",
               "answer": "80"
            },
            {
               "question": "Which computer language would you associate Django framework with?",
               "choice1": "C++",
               "choice2": "Java",
               "choice3": "C#",
               "choice4": "Python",
               "answer": "Python"
            },
            {
               "question": "Which of these programming languages is a low-level language?",
               "choice1": "Python",
               "choice2": "Pascal",
               "choice3": "Assembly",
               "choice4": "C#",
               "answer": "Assembly",
            },
            {
               "question": "Who is the original author of the realtime physics engine called PhysX?",
               "choice1": "Ageia",
               "choice2": "AMD",
               "choice3": "NovodeX",
               "choice4": "Nvidia",
               "answer": "NovodeX"
            },
            {
               "question": "Which operating system was released first?",
               "choice1": "OS/2",
               "choice2": "Windows",
               "choice3": "Mac OS",
               "choice4": "Linux",
               "answer": "Mac OS"
            },
            {
               "question": "Which data structure does FILO apply to?",
               "choice1": "Heap",
               "choice2": "Queue",
               "choice3": "Stack",
               "choice4": "Tree",
               "answer": "Stack"
            },
            {
               "question": "What does the term GPU stand for?",
               "choice1": "Graphical Proprietary Unit",
               "choice2": "Gaming Processor Unit",
               "choice3": "Graphite Producing Unit",
               "choice4": "Graphics Processing Unit",
               "answer": "Graphics Processing Unit"
            },
            {
               "question": "America Online (AOL) started out as which of these online service providers?",
               "choice1": "GEnie",
               "choice2": "CompuServe",
               "choice3": "Prodigy",
               "choice4": "Quantum Link",
               "answer": "Quantum Link"
            },
            {
               "question": "This mobile OS held the largest market share in 2012.",
               "choice1": "Android",
               "choice2": "BlackBerry",
               "choice3": "Symbian",
               "choice4": "iOS",
               "answer": "iOS"
            },
            {
               "question": "In programming, what do you call functions with the same name but different implementations?",
               "choice1": "Inheriting",
               "choice2": "Overloading",
               "choice3": "Abstracting",
               "choice4": "Overriding",
               "answer": "Overloading"
            },
            {
               "question": "How long is an IPv6 address?",
               "choice1": "128 bits",
               "choice2": "32 bits",
               "choice3": "128 bytes",
               "choice4": "64 bits",
               "answer": "128 bits"
            },
            {
               "question": "In computing, what does LAN stand for?",
               "choice1": "Local Area Network",
               "choice2": "Long Antenna Node",
               "choice3": "Land Address Navigation",
               "choice4": "Light Access Node",
               "answer": "Local Area Network"
            },
            {
               "question": "What major programming language does Unreal Engine 4 use?",
               "choice1": "C#",
               "choice2": "Assembly",
               "choice3": "ECMAScript",
               "choice4": "C++",
               "answer": "C++"
            },
            {
                "question": "What does LTS stand for in the software market?",
                "choice1": "Long Term Support",
                "choice2": "Long Taco Service",
                "choice3": "Ludicrous Transfer Speed",
                "choice4": "Turbo Speed",
                "answer": "Long Term Support"
            }
     ]
}